{
  "ObjectType Name": "Floor-Dachaufbau-Brüstung-Galerie-5450904",
  "CompilationGroupID": "c3b0cb3f28",
  "Volume [m^3]": 1.2768,
  "Largest Surface Area [m^2]": 16.0204,
  "Matched Materials with Gross Emissions (OEKOBAUDAT)": [
    {
      "Name": "Concrete paving stones/ slabs (average product) (Baustoffwerk LIMEX-VENUSBERG GmbH)",
      "ID": "91f5897a-9b31-4b93-b2ca-47b172470249",
      "Reference": "qm",
      "Density (kg/m3)": 0,
      "Bezugsgroesse": "1",
      "GWPtotal (A1)": "425.6969",
      "GWPtotal (A2)": "25.3794",
      "GWPtotal (A3)": "10.4233",
      "GWPtotal (A1-A3)": "461.4996",
      "GWPtotal (A4)": "0.0",
      "GWPtotal (A5)": "0.0",
      "GWPtotal (B1)": "0.0",
      "GWPtotal (B2)": "0.0",
      "GWPtotal (B3)": "0.0",
      "GWPtotal (B4)": "0.0",
      "GWPtotal (B5)": "0.0",
      "GWPtotal (B6)": "0.0",
      "GWPtotal (B7)": "0.0",
      "GWPtotal (C1)": "56.0036",
      "GWPtotal (C2)": "21.7222",
      "GWPtotal (C3)": "4.6507",
      "GWPtotal (C4)": "0.9909",
      "GWPbiogenic": "-20.3803",
      "GWPfossil": "1025.8095",
      "GWPtotal": "544.867",
      "Conformity": "'EN 15804+A2' / 'ISO 14025'",
      "Laenderkennung": "DE",
      "Declaration owner": "Baustoffwerk LIMEX-VENUSBERG GmbH",
      "Registrierungsnummer": "EPD-Kiwa-EE-174159-DE"
    },
    {
      "Name": "Concrete paving stones/slabs",
      "ID": "32d81066-a845-43d0-bd69-c63897f1496f",
      "Reference": "qm",
      "Density (kg/m3)": 0,
      "Bezugsgroesse": "1",
      "GWPtotal (A1)": "272.3468",
      "GWPtotal (A2)": "22.2684",
      "GWPtotal (A3)": "41.0122",
      "GWPtotal (A1-A3)": "334.8264",
      "GWPtotal (A4)": "26.5939",
      "GWPtotal (A5)": "0.0",
      "GWPtotal (B1)": "0.0",
      "GWPtotal (B2)": "0.0",
      "GWPtotal (B3)": "0.0",
      "GWPtotal (B4)": "0.0",
      "GWPtotal (B5)": "0.0",
      "GWPtotal (B6)": "0.0",
      "GWPtotal (B7)": "0.0",
      "GWPtotal (C1)": "55.9112",
      "GWPtotal (C2)": "16.501",
      "GWPtotal (C3)": "4.8061",
      "GWPtotal (C4)": "0.1567",
      "GWPbiogenic": "9.1621",
      "GWPfossil": "763.5124",
      "GWPtotal": "438.7952",
      "Conformity": "'EN 15804+A2' / 'ISO 14025'",
      "Laenderkennung": "DE",
      "Declaration owner": "H. Klostermann GmbH & Co. KG Betonwerke",
      "Registrierungsnummer": "EPD-Klostermann-319-DE, EPD-Klostermann-319-NL"
    }
  ]
}