{
  "GlobalId": "3PSzbSor5DzehfFtR_jj_6",
  "Name": "Basic-Wall-Wärmedämmung_Slentex-70-687731",
  "Volume [m^3]": 0.1582,
  "Largest Surface Area [m^2]": 2.2605,
  "Matched Materials with Gross Emissions (OEKOBAUDAT)": [
    {
      "Name": "MICROTHERM® Flexible panels range: (Semi-)Overstitched Panels, (Semi-)Quilted Panels, Slatted Panels, Aeroguard (>160 kg/m3) and Slimflex",
      "ID": "0d1d1452-7492-4508-b634-5bd0cff7edd8",
      "Reference": "kg",
      "Density (kg/m3)": "220.0",
      "Bezugsgroesse": "2.2",
      "GWPtotal (A1)": "0.0",
      "GWPtotal (A2)": "0.0",
      "GWPtotal (A3)": "0.0",
      "GWPtotal (A1-A3)": "126.4415",
      "GWPtotal (A4)": "0.0",
      "GWPtotal (A5)": "8.826",
      "GWPtotal (B1)": "0.0",
      "GWPtotal (B2)": "0.0",
      "GWPtotal (B3)": "0.0",
      "GWPtotal (B4)": "0.0",
      "GWPtotal (B5)": "0.0",
      "GWPtotal (B6)": "0.0",
      "GWPtotal (B7)": "0.0",
      "GWPtotal (C1)": "0.0",
      "GWPtotal (C2)": "0.4537",
      "GWPtotal (C3)": "0.0",
      "GWPtotal (C4)": "0.2117",
      "GWPbiogenic": "1.5419",
      "GWPfossil": "133.5199",
      "GWPtotal": "135.9329",
      "Conformity": "'DIN EN 15804+A2' / 'ISO 14025'",
      "Laenderkennung": "RER",
      "Declaration owner": "Etex Building Performance International",
      "Registrierungsnummer": "EPD-ETE-20230096-IBA1-EN"
    }
  ]
}