{
  "ObjectType Name": "M_Fixed-2800mm-x-2410mm-2800mm-x-2410mm-181096",
  "CompilationGroupID": "1c53d1eb96",
  "Volume [m^3]": 0.8872,
  "Largest Surface Area [m^2]": 26.992,
  "Matched Materials with Gross Emissions (KBOB)": [
    {
      "Name": "Isolierverglasung 2-fach, ESG, Ug-Wert 1.1 W/m2K",
      "ID": "5.01",
      "Reference": "qm",
      "Density (kg/m3)": null,
      "Global Warming Potential Total [kgCO2-eqv]": "1406.2832",
      "Global Warming Potential Manufacturing [kgCO2-eqv]": "1309.112",
      "Global Warming Potential Disposal [kgCO2-eqv]": "97.1712",
      "Biogenic Carbon [kg C]": "0.0",
      "UBP (Total)": "2348304.0",
      "UBP (Manufacturing)": "2216043.2",
      "UBP (Disposal)": "132530.72",
      "Total Renewable Primary Energy [kWh oil-eq]": "510.1488",
      "Manufacturing Renewable Primary Energy [kWh oil-eq]": "504.7504",
      "Disposal Renewable Primary Energy [kWh oil-eq]": "7.4768",
      "Total Non-Renewable Primary Energy [kWh oil-eq]": "5830.272",
      "Manufacturing Non-Renewable Primary Energy [kWh oil-eq]": "5776.288",
      "Disposal Non-Renewable Primary Energy [kWh oil-eq]": "71.7987"
    },
    {
      "Name": "Isolierverglasung 2-fach, ESG/VSG, Ug-Wert 1.1 W/m2K",
      "ID": "5.011",
      "Reference": "qm",
      "Density (kg/m3)": null,
      "Global Warming Potential Total [kgCO2-eqv]": "2351.0032",
      "Global Warming Potential Manufacturing [kgCO2-eqv]": "2170.1568",
      "Global Warming Potential Disposal [kgCO2-eqv]": "180.3066",
      "Biogenic Carbon [kg C]": "0.0",
      "UBP (Total)": "3886848.0",
      "UBP (Manufacturing)": "3670912.0",
      "UBP (Disposal)": "235640.16",
      "Total Renewable Primary Energy [kWh oil-eq]": "812.4592",
      "Manufacturing Renewable Primary Energy [kWh oil-eq]": "801.6624",
      "Disposal Renewable Primary Energy [kWh oil-eq]": "11.4446",
      "Total Non-Renewable Primary Energy [kWh oil-eq]": "10068.016",
      "Manufacturing Non-Renewable Primary Energy [kWh oil-eq]": "9960.048",
      "Disposal Non-Renewable Primary Energy [kWh oil-eq]": "111.207"
    },
    {
      "Name": "Isolierverglasung 2-fach, Ug-Wert 1.1 W/m2K, Dicke 18 mm",
      "ID": "5.009",
      "Reference": "qm",
      "Density (kg/m3)": null,
      "Global Warming Potential Total [kgCO2-eqv]": "1311.8112",
      "Global Warming Potential Manufacturing [kgCO2-eqv]": "1233.5344",
      "Global Warming Potential Disposal [kgCO2-eqv]": "76.6573",
      "Biogenic Carbon [kg C]": "0.0",
      "UBP (Total)": "2129668.8",
      "UBP (Manufacturing)": "2019001.6",
      "UBP (Disposal)": "110397.28",
      "Total Renewable Primary Energy [kWh oil-eq]": "356.2944",
      "Manufacturing Renewable Primary Energy [kWh oil-eq]": "348.1968",
      "Disposal Renewable Primary Energy [kWh oil-eq]": "7.3418",
      "Total Non-Renewable Primary Energy [kWh oil-eq]": "5263.44",
      "Manufacturing Non-Renewable Primary Energy [kWh oil-eq]": "5182.464",
      "Disposal Non-Renewable Primary Energy [kWh oil-eq]": "69.6394"
    },
    {
      "Name": "Isolierverglasung 2-fach, Ug-Wert 1.1 W/m2K, Dicke 24 mm",
      "ID": "5.001",
      "Reference": "qm",
      "Density (kg/m3)": null,
      "Global Warming Potential Total [kgCO2-eqv]": "1195.7456",
      "Global Warming Potential Manufacturing [kgCO2-eqv]": "1098.5744",
      "Global Warming Potential Disposal [kgCO2-eqv]": "97.1712",
      "Biogenic Carbon [kg C]": "0.0",
      "UBP (Total)": "1908334.4",
      "UBP (Manufacturing)": "1776073.6",
      "UBP (Disposal)": "132530.72",
      "Total Renewable Primary Energy [kWh oil-eq]": "283.416",
      "Manufacturing Renewable Primary Energy [kWh oil-eq]": "275.3184",
      "Disposal Renewable Primary Energy [kWh oil-eq]": "7.4768",
      "Total Non-Renewable Primary Energy [kWh oil-eq]": "4507.664",
      "Manufacturing Non-Renewable Primary Energy [kWh oil-eq]": "4453.68",
      "Disposal Non-Renewable Primary Energy [kWh oil-eq]": "71.7987"
    },
    {
      "Name": "Isolierverglasung 2-fach, VSG, Ug-Wert 1.1 W/m2K",
      "ID": "5.002",
      "Reference": "qm",
      "Density (kg/m3)": null,
      "Global Warming Potential Total [kgCO2-eqv]": "2140.4656",
      "Global Warming Potential Manufacturing [kgCO2-eqv]": "1959.6192",
      "Global Warming Potential Disposal [kgCO2-eqv]": "180.3066",
      "Biogenic Carbon [kg C]": "0.0",
      "UBP (Total)": "3454976.0",
      "UBP (Manufacturing)": "3212048.0",
      "UBP (Disposal)": "235640.16",
      "Total Renewable Primary Energy [kWh oil-eq]": "585.7264",
      "Manufacturing Renewable Primary Energy [kWh oil-eq]": "572.2304",
      "Disposal Renewable Primary Energy [kWh oil-eq]": "11.4446",
      "Total Non-Renewable Primary Energy [kWh oil-eq]": "8745.408",
      "Manufacturing Non-Renewable Primary Energy [kWh oil-eq]": "8637.44",
      "Disposal Non-Renewable Primary Energy [kWh oil-eq]": "111.207"
    },
    {
      "Name": "Isolierverglasung 3-fach, ESG/ESG, Ug-Wert 0.6 W/m2K",
      "ID": "5.013",
      "Reference": "qm",
      "Density (kg/m3)": null,
      "Global Warming Potential Total [kgCO2-eqv]": "2248.4336",
      "Global Warming Potential Manufacturing [kgCO2-eqv]": "2094.5792",
      "Global Warming Potential Disposal [kgCO2-eqv]": "153.8544",
      "Biogenic Carbon [kg C]": "0.0",
      "UBP (Total)": "3859856.0",
      "UBP (Manufacturing)": "3643920.0",
      "UBP (Disposal)": "207298.56",
      "Total Renewable Primary Energy [kWh oil-eq]": "904.232",
      "Manufacturing Renewable Primary Energy [kWh oil-eq]": "893.4352",
      "Disposal Renewable Primary Energy [kWh oil-eq]": "11.2557",
      "Total Non-Renewable Primary Energy [kWh oil-eq]": "9528.176",
      "Manufacturing Non-Renewable Primary Energy [kWh oil-eq]": "9420.208",
      "Disposal Non-Renewable Primary Energy [kWh oil-eq]": "108.5078"
    },
    {
      "Name": "Isolierverglasung 3-fach, ESG/ESG/ESG, Ug-Wert 0.6 W/m2K",
      "ID": "5.014",
      "Reference": "qm",
      "Density (kg/m3)": null,
      "Global Warming Potential Total [kgCO2-eqv]": "2458.9712",
      "Global Warming Potential Manufacturing [kgCO2-eqv]": "2305.1168",
      "Global Warming Potential Disposal [kgCO2-eqv]": "153.8544",
      "Biogenic Carbon [kg C]": "0.0",
      "UBP (Total)": "4291728.0",
      "UBP (Manufacturing)": "4075792.0",
      "UBP (Disposal)": "207298.56",
      "Total Renewable Primary Energy [kWh oil-eq]": "1130.9648",
      "Manufacturing Renewable Primary Energy [kWh oil-eq]": "1120.168",
      "Disposal Renewable Primary Energy [kWh oil-eq]": "11.2557",
      "Total Non-Renewable Primary Energy [kWh oil-eq]": "10850.784",
      "Manufacturing Non-Renewable Primary Energy [kWh oil-eq]": "10742.816",
      "Disposal Non-Renewable Primary Energy [kWh oil-eq]": "108.5078"
    },
    {
      "Name": "Isolierverglasung 3-fach, ESG/VSG, Ug-Wert 0.6 W/m2K",
      "ID": "5.016",
      "Reference": "qm",
      "Density (kg/m3)": null,
      "Global Warming Potential Total [kgCO2-eqv]": "2996.112",
      "Global Warming Potential Manufacturing [kgCO2-eqv]": "2780.176",
      "Global Warming Potential Disposal [kgCO2-eqv]": "236.9898",
      "Biogenic Carbon [kg C]": "0.0",
      "UBP (Total)": "4993520.0",
      "UBP (Manufacturing)": "4696608.0",
      "UBP (Disposal)": "310408.0",
      "Total Renewable Primary Energy [kWh oil-eq]": "979.8096",
      "Manufacturing Renewable Primary Energy [kWh oil-eq]": "963.6144",
      "Disposal Renewable Primary Energy [kWh oil-eq]": "15.2235",
      "Total Non-Renewable Primary Energy [kWh oil-eq]": "12524.288",
      "Manufacturing Non-Renewable Primary Energy [kWh oil-eq]": "12389.328",
      "Disposal Non-Renewable Primary Energy [kWh oil-eq]": "147.9162"
    },
    {
      "Name": "Isolierverglasung 3-fach, Ug-Wert 0.5 W/m2K, Dicke 36 mm",
      "ID": "5.003",
      "Reference": "qm",
      "Density (kg/m3)": null,
      "Global Warming Potential Total [kgCO2-eqv]": "2113.4736",
      "Global Warming Potential Manufacturing [kgCO2-eqv]": "1981.2128",
      "Global Warming Potential Disposal [kgCO2-eqv]": "132.8006",
      "Biogenic Carbon [kg C]": "0.0",
      "UBP (Total)": "3454976.0",
      "UBP (Manufacturing)": "3266032.0",
      "UBP (Disposal)": "184355.36",
      "Total Renewable Primary Energy [kWh oil-eq]": "628.9136",
      "Manufacturing Renewable Primary Energy [kWh oil-eq]": "618.1168",
      "Disposal Renewable Primary Energy [kWh oil-eq]": "11.1207",
      "Total Non-Renewable Primary Energy [kWh oil-eq]": "8637.44",
      "Manufacturing Non-Renewable Primary Energy [kWh oil-eq]": "8529.472",
      "Disposal Non-Renewable Primary Energy [kWh oil-eq]": "106.0786"
    },
    {
      "Name": "Isolierverglasung 3-fach, Ug-Wert 0.6 W/m2K, Dicke 40 mm",
      "ID": "5.012",
      "Reference": "qm",
      "Density (kg/m3)": null,
      "Global Warming Potential Total [kgCO2-eqv]": "1830.0576",
      "Global Warming Potential Manufacturing [kgCO2-eqv]": "1676.2032",
      "Global Warming Potential Disposal [kgCO2-eqv]": "153.8544",
      "Biogenic Carbon [kg C]": "0.0",
      "UBP (Total)": "2969120.0",
      "UBP (Manufacturing)": "2753184.0",
      "UBP (Disposal)": "207298.56",
      "Total Renewable Primary Energy [kWh oil-eq]": "445.368",
      "Manufacturing Renewable Primary Energy [kWh oil-eq]": "434.5712",
      "Disposal Renewable Primary Energy [kWh oil-eq]": "11.2557",
      "Total Non-Renewable Primary Energy [kWh oil-eq]": "6882.96",
      "Manufacturing Non-Renewable Primary Energy [kWh oil-eq]": "6774.992",
      "Disposal Non-Renewable Primary Energy [kWh oil-eq]": "108.5078"
    },
    {
      "Name": "Isolierverglasung 3-fach, VSG, Ug-Wert 0.6 W/m2K",
      "ID": "5.015",
      "Reference": "qm",
      "Density (kg/m3)": null,
      "Global Warming Potential Total [kgCO2-eqv]": "2780.176",
      "Global Warming Potential Manufacturing [kgCO2-eqv]": "2537.248",
      "Global Warming Potential Disposal [kgCO2-eqv]": "236.9898",
      "Biogenic Carbon [kg C]": "0.0",
      "UBP (Total)": "4534656.0",
      "UBP (Manufacturing)": "4210752.0",
      "UBP (Disposal)": "310408.0",
      "Total Renewable Primary Energy [kWh oil-eq]": "742.28",
      "Manufacturing Renewable Primary Energy [kWh oil-eq]": "728.784",
      "Disposal Renewable Primary Energy [kWh oil-eq]": "15.2235",
      "Total Non-Renewable Primary Energy [kWh oil-eq]": "11120.704",
      "Manufacturing Non-Renewable Primary Energy [kWh oil-eq]": "10958.752",
      "Disposal Non-Renewable Primary Energy [kWh oil-eq]": "147.9162"
    }
  ]
}